{
    "units": [
        {
            "id": 880,
            "names": [ "Boulder Worm" ],
            "category": "unknown",
            "phases": [ "last strike" ],
            "hit points": 200000,
            "damage": { "low": 150, "high": 300, "accuracy": 0.8, "splash chance": 1 },
            "experience when killed": 6600,
            "special abilities": [ "attack weakest target", "overrun" ]
        },
        {
            "id": 882,
            "names": [ "Giant Bat" ],
            "category": "unknown",
            "phases": [ "first strike" ],
            "hit points": 150000,
            "damage": { "low": 450, "high": 900, "accuracy": 0.9, "splash chance": 1 },
            "experience when killed": 5000,
            "special abilities": [ "overrun" ]
        },
        {
            "id": 888,
            "names": [ "Oasis Guardian" ],
            "category": "unknown",
            "phases": [ "normal" ],
            "hit points": 40000,
            "damage": { "low": 5000, "high": 10000, "accuracy": 0.9, "splash chance": 1 },
            "experience when killed": 1700,
            "special abilities": [ "overrun" ]
        },
        {
            "id": 890,
            "names": [ "Hungry Blossom" ],
            "category": "unknown",
            "phases": [ "first strike" ],
            "hit points": 10000,
            "damage": { "low": 2250, "high": 4500, "accuracy": 0.9, "splash chance": 1 },
            "experience when killed": 680,
            "special abilities": [ "attack weakest target", "overrun" ]
        },
        {
            "id": 891,
            "names": [ "Fierce Blossom" ],
            "category": "unknown",
            "phases": [ "first strike" ],
            "hit points": 15000,
            "damage": { "low": 2750, "high": 5500, "accuracy": 0.9, "splash chance": 1 },
            "experience when killed": 930,
            "special abilities": [ "attack weakest target", "overrun" ]
        },
        {
            "id": 892,
            "names": [ "Bulbous Blossom" ],
            "category": "unknown",
            "phases": [ "last strike" ],
            "hit points": 20000,
            "damage": { "low": 3250, "high": 6500, "accuracy": 0.9, "splash chance": 1 },
            "experience when killed": 920,
            "special abilities": [ "attack weakest target", "overrun" ]
        },
        {
            "id": 902,
            "names": [ "Informant" ],
            "category": "unknown",
            "phases": [ "normal" ],
            "hit points": 50000,
            "damage": { "low": 4500, "high": 9000, "accuracy": 0.9, "splash chance": 1 },
            "experience when killed": 2000,
            "special abilities": [ "overrun" ]
        },
        {
            "id": 904,
            "names": [ "Giant Sea Snake" ],
            "category": "unknown",
            "phases": [ "last strike" ],
            "hit points": 700000,
            "damage": { "low": 300, "high": 600, "accuracy": 0.8, "splash chance": 1 },
            "experience when killed": 23000,
            "special abilities": [ "overrun" ]
        },
        {
            "id": 906,
            "names": [ "Grumpy Guard" ],
            "category": "unknown",
            "phases": [ "first strike" ],
            "hit points": 25000,
            "damage": { "low": 500, "high": 1000, "accuracy": 0.9, "splash chance": 1 },
            "experience when killed": 910,
            "special abilities": [ "attack weakest target", "overrun" ]
        },
        {
            "id": 908,
            "names": [ "Insane Guard" ],
            "category": "unknown",
            "phases": [ "last strike" ],
            "hit points": 50000,
            "damage": { "low": 250, "high": 500, "accuracy": 0.9, "splash chance": 1 },
            "experience when killed": 1700,
            "special abilities": [ "attack weakest target", "overrun" ]
        }
    ]
}
